MANIFEST.in
README.md
setup.py
dupe_eraser/__init__.py
dupe_eraser/main.py
dupe_eraser.egg-info/PKG-INFO
dupe_eraser.egg-info/SOURCES.txt
dupe_eraser.egg-info/dependency_links.txt
dupe_eraser.egg-info/entry_points.txt
dupe_eraser.egg-info/requires.txt
dupe_eraser.egg-info/top_level.txt
dupe_eraser/res/default_values.json
dupe_eraser/res/global_variables.json
dupe_eraser/res/output_messages.json
dupe_eraser/res/parameters_documentation.json
dupe_eraser/res/parameters_names.json
dupe_eraser/src/__init__.py
dupe_eraser/src/core/__init__.py
dupe_eraser/src/core/files_eraser.py
dupe_eraser/src/core/files_finder.py
dupe_eraser/src/core/hashing_algorithms.py
dupe_eraser/src/core/initialization/__init__.py
dupe_eraser/src/core/initialization/args_cleaner.py
dupe_eraser/src/core/initialization/args_parser.py
dupe_eraser/src/getters/__init__.py
dupe_eraser/src/getters/environment.py
dupe_eraser/src/getters/get_default_value.py
dupe_eraser/src/getters/get_global_variable.py
dupe_eraser/src/getters/get_output_message.py
dupe_eraser/src/getters/get_parameter_documentation.py
dupe_eraser/src/getters/get_parameter_name.py